spycone/BioNetwork.py
spycone/DataSet.py
spycone/__config__.py
spycone/__init__.py
spycone/clustering.py
spycone/connectivity.py
spycone/go_terms.py
spycone/iso.py
spycone/preprocess.py
spycone/run_domino.py
spycone/setup.py
spycone/splicingfactor.py
spycone/visualize.py
spycone/DOMINO/__init__.py
spycone/DOMINO/setup.py
spycone/DOMINO/src/__init__.py
spycone/DOMINO/src/constants.py
spycone/DOMINO/src/runner.py
spycone/DOMINO/src/core/__init__.py
spycone/DOMINO/src/core/domino.py
spycone/DOMINO/src/core/network_builder.py
spycone/DOMINO/src/core/preprocess_slices.py
spycone/DOMINO/src/data/__init__.py
spycone/DOMINO/src/utils/__init__.py
spycone/DOMINO/src/utils/ensembl2gene_symbol.py
spycone/DOMINO/src/utils/graph_influence_linear_th.py
spycone/DOMINO/src/utils/scripts.py
spycone/DOMINO/src/utils/visualize_modules.py
spycone/_NEASE/__init__.py
spycone/_NEASE/setup.py
spycone/_NEASE/nease/__init__.py
spycone/_NEASE/nease/functions.py
spycone/_NEASE/nease/load.py
spycone/_NEASE/nease/nease.py
spycone/_NEASE/nease/process.py
spycone/_NEASE/nease/data/database/Human
spycone/_NEASE/nease/data/network/PPI_Human.pkl
spycone/_NEASE/nease/data/network/graph_human.pkl
spycone/_NEASE/nease/data/pathways/pathways_human
spycone/_clustering/__init__.py
spycone/_clustering/build_cluster.py
spycone/_clustering/clusterobj.py
spycone/_clustering/inverseshortestpath.py
spycone/_clustering/kmedoids.py
spycone/_clustering/setup.py
spycone/_clustering/similarities.py
spycone/_clustering/skclara.py
spycone/_feature/__init__.py
spycone/_feature/get_features.py
spycone/_feature/_connectivity/__init__.py
spycone/_feature/_connectivity/setup.py
spycone/_fitness/__init__.py
spycone/_fitness/fitness_score.py
spycone/_fitness/scaler.py
spycone/_preprocessing/__init__.py
spycone/_preprocessing/_discretization.py
spycone/_prototype/__init__.py
spycone/_prototype/prototype_builder.py
spycone/_shuffle/__init__.py
spycone/_shuffle/setup.py
spycone/_shuffle/shuffle.py
spycone/_util_stat/__init__.py
spycone-0.2.1.dist-info/LICENSE
spycone-0.2.1.dist-info/METADATA
spycone-0.2.1.dist-info/WHEEL
spycone-0.2.1.dist-info/top_level.txt
spycone-0.2.1.dist-info/RECORD
