Metadata-Version: 2.1
Name: spycone
Version: 0.2.1
Summary: A splicing-aware time course network enricher
Home-page: https://github.com/yollct/spycone.git
Author: Chit Tong Lio
Author-email: ct7298@gmail.com
License: GPLv3
Classifier: Programming Language :: Python :: 3
Classifier: Programming Language :: Python :: 3.7
Classifier: License :: OSI Approved :: GNU General Public License v3 (GPLv3)
Classifier: Topic :: Scientific/Engineering :: Bio-Informatics
Requires-Python: >=3.7
License-File: LICENSE
Requires-Dist: pandas >=1.0.1
Requires-Dist: numpy >=1.22
Requires-Dist: seaborn
Requires-Dist: scikit-learn <=1.2.2
Requires-Dist: scikit-learn-extra >=0.1.0
Requires-Dist: networkx >=2.4
Requires-Dist: matplotlib >=3.1.3
Requires-Dist: gprofiler-official >=1.0.0
Requires-Dist: scipy >=1.4.1
Requires-Dist: statsmodels >=0.11.0
Requires-Dist: tslearn >=0.5.2
Requires-Dist: python-louvain
Requires-Dist: plotly >=4.14.3
Requires-Dist: pydot >=1.4.2
Requires-Dist: biopython <=1.80
Requires-Dist: gtfparse
Requires-Dist: joblib
Requires-Dist: nease
